streaming_spouts/__init__.py
streaming_spouts/amqp.py
streaming_spouts/http_polling.py
streaming_spouts/kafka.py
streaming_spouts/mqtt.py
streaming_spouts/quic.py
streaming_spouts/redis_pubsub.py
streaming_spouts/redis_streams.py
streaming_spouts/sns.py
streaming_spouts/sqs.py
streaming_spouts/udp.py
streaming_spouts/webhook.py
streaming_spouts/websocket.py
genius_streaming_spouts-0.1.0.dist-info/METADATA
genius_streaming_spouts-0.1.0.dist-info/WHEEL
genius_streaming_spouts-0.1.0.dist-info/top_level.txt
genius_streaming_spouts-0.1.0.dist-info/RECORD
