Metadata-Version: 2.1
Name: genius-streaming-spouts
Version: 0.1.0
Summary: Streaming spouts for geniusrise
Home-page: https://github.com/ixaxaar/streaming-spouts
Author: ixaxaar
Author-email: ixaxaar@geniusrise.ai
Classifier: Programming Language :: Python :: 3
Classifier: License :: OSI Approved :: MIT License
Classifier: Operating System :: OS Independent
Requires-Python: >=3.10
